ninja_bear_language_c/__init__.py
ninja_bear_language_c/config.py
ninja_bear_language_c/generator.py
ninja_bear_language_c-0.1.0.dist-info/LICENSE
ninja_bear_language_c-0.1.0.dist-info/METADATA
ninja_bear_language_c-0.1.0.dist-info/WHEEL
ninja_bear_language_c-0.1.0.dist-info/entry_points.txt
ninja_bear_language_c-0.1.0.dist-info/top_level.txt
ninja_bear_language_c-0.1.0.dist-info/RECORD
